{
  "author": [
    "The Tsubaki Bot Team"
  ],
  "description": "Very few commands, but loads all the monster data stored in Tsubaki.",
  "end_user_data_statement": "ID Query Settings are stored in this cog.",
  "install_msg": "Use [p]dbcog setdatafile if it's applicable to you.",
  "short": "Loads monster data",
  "min_bot_version": "3.4.0",
  "max_bot_version": "0.0.0",
  "min_python_version": [
    3,
    8,
    1
  ],
  "hidden": false,
  "disabled": false,
  "required_cogs": {
    "globaladmin": "https://github.com/TsubakiBotPad/core-cogs"
  },
  "requirements": [
    "python-Levenshtein-wheels",
    "tsutils>=5.0.0",
    "pytz",
    "regex",
    "romkan",
    "networkx"
  ],
  "tags": [
    "PAD"
  ]
}
